check/check.py
check/ops.txt
paddlejsmodelcheck-0.0.11.dist-info/METADATA
paddlejsmodelcheck-0.0.11.dist-info/WHEEL
paddlejsmodelcheck-0.0.11.dist-info/entry_points.txt
paddlejsmodelcheck-0.0.11.dist-info/top_level.txt
paddlejsmodelcheck-0.0.11.dist-info/RECORD
