Metadata-Version: 2.1
Name: paddlejsmodelcheck
Version: 0.0.11
Summary: Paddlejs model check
Home-page: https://github.com/PaddlePaddle/Paddle.js
Author: paddlejs
Author-email: 382248373@qq.com
License: UNKNOWN
Platform: UNKNOWN
Classifier: Programming Language :: Python
Classifier: Programming Language :: Python :: 3
Classifier: License :: OSI Approved :: MIT License
Classifier: Operating System :: OS Independent
Requires-Python: >=3.6
Requires-Dist: paddlepaddle (>=2.0.0)
Requires-Dist: numpy
